danbooru/__init__.py
danbooru/__vars__.py
danbooru/booru.py
danbooru/exceptions.py
danbooru/types/Danbooru_API.py
danbooru/types/Danbooru_Types.py
danbooru/types/__init__.py
danbooru-0.1.1.dist-info/LICENSE
danbooru-0.1.1.dist-info/METADATA
danbooru-0.1.1.dist-info/WHEEL
danbooru-0.1.1.dist-info/top_level.txt
danbooru-0.1.1.dist-info/RECORD
