Metadata-Version: 2.1
Name: danbooru
Version: 0.1.1
Summary: Unofficial https://danbooru.donmai.us Package
Home-page: https://github.com/TaprisSugarbell/Danbooru
Author: SayuOgiwara
Author-email: anonesayu@gmail.com
Project-URL: Issue tracker, https://github.com/TaprisSugarbell/Danbooru/issues
License-File: LICENSE
Requires-Dist: beautifulsoup4
Requires-Dist: cloudscraper
